flyover/Entities.py
flyover/MapGenerator.py
flyover/__init__.py
flyover/__main__.py
flyover/assets/__init__.py
flyover/assets/sound_effects/__init__.py
flyover/assets/sound_effects/ogg/__init__.py
flyover/assets/sound_effects/ogg/explosion_1.ogg
flyover/assets/sound_effects/ogg/explosion_2.ogg
flyover/assets/sound_effects/ogg/explosion_3.ogg
flyover/assets/sound_effects/ogg/player_death.ogg
flyover/assets/sound_effects/ogg/shooting_1.ogg
flyover/assets/sound_effects/ogg/shooting_2.ogg
flyover/assets/sound_effects/ogg/shooting_3.ogg
flyover/assets/sprites/Mig21.png
flyover/assets/sprites/Mig21_left.png
flyover/assets/sprites/Mig21_right.png
flyover/assets/sprites/Mig35.png
flyover/assets/sprites/Mig35_left.png
flyover/assets/sprites/Mig35_right.png
flyover/assets/sprites/__init__.py
flyover/assets/sprites/player.png
flyover/assets/sprites/player_left.png
flyover/assets/sprites/player_right.png
flyover/assets/tiles/Grass.png
flyover/assets/tiles/Sea.png
flyover/assets/tiles/__init__.py
flyover_game-0.11.dist-info/LICENSE
flyover_game-0.11.dist-info/METADATA
flyover_game-0.11.dist-info/WHEEL
flyover_game-0.11.dist-info/entry_points.txt
flyover_game-0.11.dist-info/top_level.txt
flyover_game-0.11.dist-info/RECORD
