Metadata-Version: 2.1
Name: flyover-game
Version: 0.11
Summary: Shoot as many enemy planes as you can before they get you!
Home-page: https://github.com/stevetasticsteve/Flyover
Author: Stephen Stanley
Author-email: stevetasticsteve@gmail.com
License: GPL version 3
Platform: UNKNOWN
Classifier: License :: OSI Approved :: GNU General Public License v3 (GPLv3)
Classifier: Programming Language :: Python :: 3
Requires-Dist: pygame
